importer_local/ImportersLocal.py
importer_local/__init__.py
importer_local/importer_sync_conflict_resolution.py
importer_local-0.0.68.dist-info/METADATA
importer_local-0.0.68.dist-info/WHEEL
importer_local-0.0.68.dist-info/top_level.txt
importer_local-0.0.68.dist-info/RECORD
