Metadata-Version: 2.1
Name: importer-local
Version: 0.0.68
Summary: PyPI Package for Circles circles_importer Local/Remote Python
Home-page: https://github.com/circles-zone/importer-local-python-package
Author: Circlez
Author-email: info@circlez.ai
Classifier: Programming Language :: Python :: 3
Classifier: License :: Other/Proprietary License
Classifier: Operating System :: OS Independent
Requires-Dist: logger-local >=0.0.75
Requires-Dist: database-mysql-local >=0.0.134
Requires-Dist: location-local >=0.0.60
